apollo3zehn_package_management/__init__.py
apollo3zehn_package_management/_encoder.py
apollo3zehn_package_management/_package_management.py
apollo3zehn_package_management/_services.py
apollo3zehn_package_management/_typedefs.py
apollo3zehn_package_management-1.0.0b5.dist-info/METADATA
apollo3zehn_package_management-1.0.0b5.dist-info/WHEEL
apollo3zehn_package_management-1.0.0b5.dist-info/top_level.txt
apollo3zehn_package_management-1.0.0b5.dist-info/RECORD
